bigbrain/__init__.py
bigbrain/ai.py
bigbrain-0.1.1.dist-info/LICENSE
bigbrain-0.1.1.dist-info/METADATA
bigbrain-0.1.1.dist-info/WHEEL
bigbrain-0.1.1.dist-info/top_level.txt
bigbrain-0.1.1.dist-info/RECORD
