Metadata-Version: 2.1
Name: bigbrain
Version: 0.1.1
Summary: A toolbox for learning anything and everything from data.
Home-page: https://github.com/gmischl1/bigbrain
Author: ('Joanna Guo', 'Gavin Mischler')
Author-email: gavin.m.mischler@gmail.com
License: Apache License 2.0
Platform: UNKNOWN
Classifier: Development Status :: 3 - Alpha
Classifier: Intended Audience :: Science/Research
Classifier: Topic :: Scientific/Engineering :: Mathematics
Classifier: License :: OSI Approved :: Apache Software License
Classifier: Programming Language :: Python :: 3
Classifier: Programming Language :: Python :: 3.6
Classifier: Programming Language :: Python :: 3.7
Requires-Dist: numpy
Requires-Dist: scikit-learn
